<annotation>
    <folder>train</folder>
    <filename>UNADJUSTEDNONRAW_thumb_10a4.jpg</filename>
    <size>
        <width>768</width>
        <height>1024</height>
        <depth>3</depth>
    </size>
    <segmented>0</segmented>
    <object>
        <name>scooter</name>
        <pose>Unspecified</pose>
        <truncated>0</truncated>
        <occluded>0</occluded>
        <difficult>0</difficult>
        <polygon>
            <x1>384</x1>
            <y1>449</y1>
            <x2>316</x2>
            <y2>418</y2>
            <x3>315</x3>
            <y3>440</y3>
            <x4>360</x4>
            <y4>466</y4>
            <x5>371</x5>
            <y5>470</y5>
            <x6>377</x6>
            <y6>472</y6>
            <x7>380</x7>
            <y7>470</y7>
            <x8>394</x8>
            <y8>467</y8>
            <x9>398</x9>
            <y9>465</y9>
            <x10>404</x10>
            <y10>460</y10>
            <x11>408</x11>
            <y11>457</y11>
            <x12>413</x12>
            <y12>451</y12>
            <x13>420</x13>
            <y13>445</y13>
            <x14>421</x14>
            <y14>451</y14>
            <x15>420</x15>
            <y15>455</y15>
            <x16>418</x16>
            <y16>461</y16>
            <x17>419</x17>
            <y17>464</y17>
            <x18>414</x18>
            <y18>469</y18>
            <x19>408</x19>
            <y19>472</y19>
            <x20>401</x20>
            <y20>478</y20>
            <x21>400</x21>
            <y21>485</y21>
            <x22>398</x22>
            <y22>494</y22>
            <x23>399</x23>
            <y23>504</y23>
            <x24>406</x24>
            <y24>516</y24>
            <x25>417</x25>
            <y25>522</y25>
            <x26>425</x26>
            <y26>525</y26>
            <x27>435</x27>
            <y27>525</y27>
            <x28>442</x28>
            <y28>521</y28>
            <x29>451</x29>
            <y29>515</y29>
            <x30>458</x30>
            <y30>508</y30>
            <x31>460</x31>
            <y31>501</y31>
            <x32>456</x32>
            <y32>481</y32>
            <x33>454</x33>
            <y33>474</y33>
            <x34>452</x34>
            <y34>472</y34>
            <x35>455</x35>
            <y35>471</y35>
            <x36>452</x36>
            <y36>465</y36>
            <x37>444</x37>
            <y37>460</y37>
            <x38>439</x38>
            <y38>458</y38>
            <x39>437</x39>
            <y39>427</y39>
            <x40>437</x40>
            <y40>406</y40>
            <x41>440</x41>
            <y41>407</y41>
            <x42>441</x42>
            <y42>408</y42>
            <x43>447</x43>
            <y43>410</y43>
            <x44>452</x44>
            <y44>407</y44>
            <x45>453</x45>
            <y45>401</y45>
            <x46>452</x46>
            <y46>355</y46>
            <x47>449</x47>
            <y47>352</y47>
            <x48>444</x48>
            <y48>350</y48>
            <x49>442</x49>
            <y49>354</y49>
            <x50>439</x50>
            <y50>354</y50>
            <x51>433</x51>
            <y51>165</y51>
            <x52>435</x52>
            <y52>162</y52>
            <x53>436</x53>
            <y53>160</y53>
            <x54>435</x54>
            <y54>156</y54>
            <x55>438</x55>
            <y55>154</y55>
            <x56>441</x56>
            <y56>151</y56>
            <x57>444</x57>
            <y57>146</y57>
            <x58>446</x58>
            <y58>142</y58>
            <x59>448</x59>
            <y59>139</y59>
            <x60>449</x60>
            <y60>136</y60>
            <x61>448</x61>
            <y61>133</y61>
            <x62>445</x62>
            <y62>129</y62>
            <x63>443</x63>
            <y63>129</y63>
            <x64>439</x64>
            <y64>132</y64>
            <x65>435</x65>
            <y65>137</y65>
            <x66>432</x66>
            <y66>141</y66>
            <x67>429</x67>
            <y67>144</y67>
            <x68>427</x68>
            <y68>144</y68>
            <x69>426</x69>
            <y69>144</y69>
            <x70>421</x70>
            <y70>144</y70>
            <x71>416</x71>
            <y71>146</y71>
            <x72>413</x72>
            <y72>147</y72>
            <x73>411</x73>
            <y73>150</y73>
            <x74>412</x74>
            <y74>154</y74>
            <x75>412</x75>
            <y75>159</y75>
            <x76>414</x76>
            <y76>222</y76>
            <x77>414</x77>
            <y77>231</y77>
            <x78>414</x78>
            <y78>234</y78>
            <x79>413</x79>
            <y79>239</y79>
            <x80>411</x80>
            <y80>242</y80>
            <x81>406</x81>
            <y81>248</y81>
            <x82>400</x82>
            <y82>254</y82>
            <x83>396</x83>
            <y83>259</y83>
            <x84>395</x84>
            <y84>266</y84>
            <x85>395</x85>
            <y85>273</y85>
            <x86>395</x86>
            <y86>279</y86>
            <x87>395</x87>
            <y87>294</y87>
            <x88>395</x88>
            <y88>302</y88>
            <x89>395</x89>
            <y89>317</y89>
            <x90>395</x90>
            <y90>329</y90>
            <x91>396</x91>
            <y91>343</y91>
            <x92>399</x92>
            <y92>352</y92>
            <x93>407</x93>
            <y93>362</y93>
            <x94>411</x94>
            <y94>366</y94>
            <x95>415</x95>
            <y95>368</y95>
            <x96>417</x96>
            <y96>374</y96>
            <x97>418</x97>
            <y97>380</y97>
            <x98>418</x98>
            <y98>387</y98>
            <x99>418</x99>
            <y99>390</y99>
            <x100>417</x100>
            <y100>396</y100>
            <x101>418</x101>
            <y101>406</y101>
            <x102>419</x102>
            <y102>414</y102>
            <x103>405</x103>
            <y103>432</y103>
            <x104>399</x104>
            <y104>438</y104>
            <x105>391</x105>
            <y105>442</y105>
        </polygon>
        <bndbox>
            <xmin>315</xmin>
            <ymin>129</ymin>
            <xmax>460</xmax>
            <ymax>525</ymax>
        </bndbox>
    </object>
    <object>
        <name>scooter</name>
        <pose>Unspecified</pose>
        <truncated>0</truncated>
        <occluded>0</occluded>
        <difficult>0</difficult>
        <polygon>
            <x1>294</x1>
            <y1>134</y1>
            <x2>290</x2>
            <y2>139</y2>
            <x3>286</x3>
            <y3>142</y3>
            <x4>283</x4>
            <y4>144</y4>
            <x5>280</x5>
            <y5>145</y5>
            <x6>278</x6>
            <y6>145</y6>
            <x7>274</x7>
            <y7>147</y7>
            <x8>273</x8>
            <y8>150</y8>
            <x9>273</x9>
            <y9>153</y9>
            <x10>271</x10>
            <y10>153</y10>
            <x11>267</x11>
            <y11>154</y11>
            <x12>266</x12>
            <y12>154</y12>
            <x13>264</x13>
            <y13>155</y13>
            <x14>262</x14>
            <y14>157</y14>
            <x15>272</x15>
            <y15>332</y15>
            <x16>274</x16>
            <y16>365</y16>
            <x17>273</x17>
            <y17>370</y17>
            <x18>271</x18>
            <y18>370</y18>
            <x19>273</x19>
            <y19>378</y19>
            <x20>273</x20>
            <y20>384</y20>
            <x21>275</x21>
            <y21>391</y21>
            <x22>274</x22>
            <y22>396</y22>
            <x23>271</x23>
            <y23>401</y23>
            <x24>269</x24>
            <y24>407</y24>
            <x25>267</x25>
            <y25>412</y25>
            <x26>267</x26>
            <y26>418</y26>
            <x27>269</x27>
            <y27>425</y27>
            <x28>271</x28>
            <y28>431</y28>
            <x29>273</x29>
            <y29>436</y29>
            <x30>275</x30>
            <y30>440</y30>
            <x31>276</x31>
            <y31>444</y31>
            <x32>277</x32>
            <y32>450</y32>
            <x33>279</x33>
            <y33>451</y33>
            <x34>279</x34>
            <y34>457</y34>
            <x35>280</x35>
            <y35>461</y35>
            <x36>266</x36>
            <y36>477</y36>
            <x37>258</x37>
            <y37>482</y37>
            <x38>252</x38>
            <y38>485</y38>
            <x39>250</x39>
            <y39>488</y39>
            <x40>188</x40>
            <y40>453</y40>
            <x41>183</x41>
            <y41>450</y41>
            <x42>179</x42>
            <y42>447</y42>
            <x43>172</x43>
            <y43>429</y43>
            <x44>169</x44>
            <y44>422</y44>
            <x45>162</x45>
            <y45>417</y45>
            <x46>160</x46>
            <y46>413</y46>
            <x47>155</x47>
            <y47>413</y47>
            <x48>152</x48>
            <y48>411</y48>
            <x49>145</x49>
            <y49>413</y49>
            <x50>141</x50>
            <y50>415</y50>
            <x51>139</x51>
            <y51>418</y51>
            <x52>140</x52>
            <y52>419</y52>
            <x53>143</x53>
            <y53>420</y53>
            <x54>146</x54>
            <y54>420</y54>
            <x55>148</x55>
            <y55>423</y55>
            <x56>148</x56>
            <y56>425</y56>
            <x57>144</x57>
            <y57>426</y57>
            <x58>141</x58>
            <y58>428</y58>
            <x59>137</x59>
            <y59>432</y59>
            <x60>136</x60>
            <y60>438</y60>
            <x61>137</x61>
            <y61>446</y61>
            <x62>138</x62>
            <y62>454</y62>
            <x63>140</x63>
            <y63>463</y63>
            <x64>144</x64>
            <y64>472</y64>
            <x65>148</x65>
            <y65>475</y65>
            <x66>156</x66>
            <y66>479</y66>
            <x67>162</x67>
            <y67>479</y67>
            <x68>166</x68>
            <y68>477</y68>
            <x69>169</x69>
            <y69>475</y69>
            <x70>227</x70>
            <y70>512</y70>
            <x71>232</x71>
            <y71>514</y71>
            <x72>238</x72>
            <y72>515</y72>
            <x73>248</x73>
            <y73>513</y73>
            <x74>256</x74>
            <y74>511</y74>
            <x75>263</x75>
            <y75>510</y75>
            <x76>268</x76>
            <y76>508</y76>
            <x77>274</x77>
            <y77>505</y77>
            <x78>279</x78>
            <y78>496</y78>
            <x79>280</x79>
            <y79>495</y79>
            <x80>280</x80>
            <y80>495</y80>
            <x81>280</x81>
            <y81>498</y81>
            <x82>282</x82>
            <y82>502</y82>
            <x83>281</x83>
            <y83>504</y83>
            <x84>280</x84>
            <y84>509</y84>
            <x85>277</x85>
            <y85>511</y85>
            <x86>272</x86>
            <y86>514</y86>
            <x87>268</x87>
            <y87>517</y87>
            <x88>265</x88>
            <y88>521</y88>
            <x89>262</x89>
            <y89>528</y89>
            <x90>260</x90>
            <y90>534</y90>
            <x91>258</x91>
            <y91>540</y91>
            <x92>257</x92>
            <y92>547</y92>
            <x93>259</x93>
            <y93>552</y93>
            <x94>262</x94>
            <y94>561</y94>
            <x95>275</x95>
            <y95>572</y95>
            <x96>282</x96>
            <y96>577</y96>
            <x97>287</x97>
            <y97>579</y97>
            <x98>293</x98>
            <y98>580</y98>
            <x99>301</x99>
            <y99>578</y99>
            <x100>305</x100>
            <y100>577</y100>
            <x101>312</x101>
            <y101>574</y101>
            <x102>320</x102>
            <y102>569</y102>
            <x103>326</x103>
            <y103>563</y103>
            <x104>327</x104>
            <y104>555</y104>
            <x105>329</x105>
            <y105>543</y105>
            <x106>329</x106>
            <y106>535</y106>
            <x107>325</x107>
            <y107>530</y107>
            <x108>326</x108>
            <y108>528</y108>
            <x109>321</x109>
            <y109>521</y109>
            <x110>320</x110>
            <y110>520</y110>
            <x111>322</x111>
            <y111>519</y111>
            <x112>323</x112>
            <y112>517</y112>
            <x113>320</x113>
            <y113>514</y113>
            <x114>316</x114>
            <y114>512</y114>
            <x115>312</x115>
            <y115>510</y115>
            <x116>306</x116>
            <y116>507</y116>
            <x117>302</x117>
            <y117>505</y117>
            <x118>298</x118>
            <y118>451</y118>
            <x119>299</x119>
            <y119>447</y119>
            <x120>301</x120>
            <y120>448</y120>
            <x121>306</x121>
            <y121>449</y121>
            <x122>311</x122>
            <y122>449</y122>
            <x123>317</x123>
            <y123>447</y123>
            <x124>315</x124>
            <y124>391</y124>
            <x125>310</x125>
            <y125>388</y125>
            <x126>308</x126>
            <y126>387</y126>
            <x127>304</x127>
            <y127>388</y127>
            <x128>301</x128>
            <y128>388</y128>
            <x129>298</x129>
            <y129>385</y129>
            <x130>286</x130>
            <y130>172</y130>
            <x131>287</x131>
            <y131>168</y131>
            <x132>290</x132>
            <y132>169</y132>
            <x133>291</x133>
            <y133>161</y133>
            <x134>293</x134>
            <y134>159</y134>
            <x135>297</x135>
            <y135>158</y135>
            <x136>301</x136>
            <y136>155</y136>
            <x137>305</x137>
            <y137>152</y137>
            <x138>306</x138>
            <y138>144</y138>
            <x139>307</x139>
            <y139>140</y139>
            <x140>305</x140>
            <y140>134</y140>
            <x141>299</x141>
            <y141>132</y141>
            <x142>296</x142>
            <y142>133</y142>
        </polygon>
        <bndbox>
            <xmin>136</xmin>
            <ymin>132</ymin>
            <xmax>329</xmax>
            <ymax>580</ymax>
        </bndbox>
    </object>
    <object>
        <name>scooter</name>
        <pose>Unspecified</pose>
        <truncated>0</truncated>
        <occluded>0</occluded>
        <difficult>0</difficult>
        <polygon>
            <x1>9</x1>
            <y1>106</y1>
            <x2>10</x2>
            <y2>111</y2>
            <x3>11</x3>
            <y3>113</y3>
            <x4>11</x4>
            <y4>117</y4>
            <x5>10</x5>
            <y5>118</y5>
            <x6>11</x6>
            <y6>121</y6>
            <x7>12</x7>
            <y7>125</y7>
            <x8>13</x8>
            <y8>126</y8>
            <x9>14</x9>
            <y9>129</y9>
            <x10>15</x10>
            <y10>132</y10>
            <x11>17</x11>
            <y11>135</y11>
            <x12>18</x12>
            <y12>135</y12>
            <x13>19</x13>
            <y13>136</y13>
            <x14>20</x14>
            <y14>141</y14>
            <x15>20</x15>
            <y15>143</y15>
            <x16>22</x16>
            <y16>148</y16>
            <x17>26</x17>
            <y17>157</y17>
            <x18>27</x18>
            <y18>163</y18>
            <x19>29</x19>
            <y19>169</y19>
            <x20>29</x20>
            <y20>173</y20>
            <x21>29</x21>
            <y21>174</y21>
            <x22>29</x22>
            <y22>178</y22>
            <x23>30</x23>
            <y23>183</y23>
            <x24>30</x24>
            <y24>188</y24>
            <x25>31</x25>
            <y25>192</y25>
            <x26>31</x26>
            <y26>193</y26>
            <x27>30</x27>
            <y27>193</y27>
            <x28>28</x28>
            <y28>194</y28>
            <x29>26</x29>
            <y29>196</y29>
            <x30>24</x30>
            <y30>196</y30>
            <x31>22</x31>
            <y31>192</y31>
            <x32>19</x32>
            <y32>191</y32>
            <x33>18</x33>
            <y33>190</y33>
            <x34>17</x34>
            <y34>191</y34>
            <x35>13</x35>
            <y35>190</y35>
            <x36>12</x36>
            <y36>191</y36>
            <x37>10</x37>
            <y37>193</y37>
            <x38>8</x38>
            <y38>196</y38>
            <x39>9</x39>
            <y39>197</y39>
            <x40>10</x40>
            <y40>198</y40>
            <x41>10</x41>
            <y41>199</y41>
            <x42>9</x42>
            <y42>200</y42>
            <x43>9</x43>
            <y43>202</y43>
            <x44>9</x44>
            <y44>205</y44>
            <x45>10</x45>
            <y45>207</y45>
            <x46>13</x46>
            <y46>208</y46>
            <x47>14</x47>
            <y47>210</y47>
            <x48>15</x48>
            <y48>211</y48>
            <x49>17</x49>
            <y49>212</y49>
            <x50>20</x50>
            <y50>212</y50>
            <x51>22</x51>
            <y51>213</y51>
            <x52>23</x52>
            <y52>210</y52>
            <x53>23</x53>
            <y53>209</y53>
            <x54>23</x54>
            <y54>209</y54>
            <x55>22</x55>
            <y55>206</y55>
            <x56>24</x56>
            <y56>205</y56>
            <x57>27</x57>
            <y57>205</y57>
            <x58>33</x58>
            <y58>202</y58>
            <x59>35</x59>
            <y59>201</y59>
            <x60>37</x60>
            <y60>200</y60>
            <x61>37</x61>
            <y61>199</y61>
            <x62>36</x62>
            <y62>195</y62>
            <x63>37</x63>
            <y63>192</y63>
            <x64>35</x64>
            <y64>176</y64>
            <x65>34</x65>
            <y65>171</y65>
            <x66>24</x66>
            <y66>136</y66>
            <x67>18</x67>
            <y67>113</y67>
            <x68>15</x68>
            <y68>109</y68>
            <x69>14</x69>
            <y69>105</y69>
            <x70>16</x70>
            <y70>106</y70>
            <x71>17</x71>
            <y71>105</y71>
            <x72>19</x72>
            <y72>106</y72>
            <x73>20</x73>
            <y73>104</y73>
            <x74>17</x74>
            <y74>103</y74>
            <x75>16</x75>
            <y75>102</y75>
            <x76>12</x76>
            <y76>103</y76>
            <x77>9</x77>
            <y77>103</y77>
            <x78>7</x78>
            <y78>103</y78>
            <x79>6</x79>
            <y79>105</y79>
            <x80>4</x80>
            <y80>106</y80>
            <x81>4</x81>
            <y81>107</y81>
            <x82>6</x82>
            <y82>108</y82>
        </polygon>
        <bndbox>
            <xmin>4</xmin>
            <ymin>102</ymin>
            <xmax>37</xmax>
            <ymax>213</ymax>
        </bndbox>
    </object>
</annotation>